setup.py
invoicetopdf.egg-info/PKG-INFO
invoicetopdf.egg-info/SOURCES.txt
invoicetopdf.egg-info/dependency_links.txt
invoicetopdf.egg-info/requires.txt
invoicetopdf.egg-info/top_level.txt
invoicing/__init__.py
invoicing/invoice.py